my_pipomatic_func.py
my_pipomatic_func-1.6.dist-info/METADATA
my_pipomatic_func-1.6.dist-info/WHEEL
my_pipomatic_func-1.6.dist-info/top_level.txt
my_pipomatic_func-1.6.dist-info/RECORD
