Metadata-Version: 2.1
Name: my-pipomatic-func
Version: 1.6
Summary: Sample description
Home-page: http://www.example.com
Author: Hudge
Author-email: 
License: UNKNOWN
Platform: UNKNOWN
Classifier: Programming Language :: Python :: 3
Classifier: License :: OSI Approved :: MIT License
Classifier: Operating System :: OS Independent
